AndroidBaizhanJingdian/README.md
AndroidBaizhanJingdian/__init__.py
AndroidBaizhanJingdian/__main__.py
AndroidBaizhanJingdian/file.epub
AndroidBaizhanJingdian/index.html
AndroidBaizhanJingdian/css/__init__.py
AndroidBaizhanJingdian/css/annotations.css
AndroidBaizhanJingdian/css/main.css
AndroidBaizhanJingdian/css/normalize.css
AndroidBaizhanJingdian/css/popup.css
AndroidBaizhanJingdian/font/__init__.py
AndroidBaizhanJingdian/font/fontello.eot
AndroidBaizhanJingdian/font/fontello.svg
AndroidBaizhanJingdian/font/fontello.ttf
AndroidBaizhanJingdian/font/fontello.woff
AndroidBaizhanJingdian/img/__init__.py
AndroidBaizhanJingdian/img/annotator-glyph-sprite.png
AndroidBaizhanJingdian/img/annotator-icon-sprite.png
AndroidBaizhanJingdian/img/apple-touch-icon.png
AndroidBaizhanJingdian/img/cancelfullscreen.png
AndroidBaizhanJingdian/img/close.png
AndroidBaizhanJingdian/img/fullscreen.png
AndroidBaizhanJingdian/img/loader.gif
AndroidBaizhanJingdian/img/menu-icon.png
AndroidBaizhanJingdian/img/save.png
AndroidBaizhanJingdian/img/saved.png
AndroidBaizhanJingdian/img/settings-s.png
AndroidBaizhanJingdian/img/settings.png
AndroidBaizhanJingdian/img/star.png
AndroidBaizhanJingdian/js/__init__.py
AndroidBaizhanJingdian/js/epub.js
AndroidBaizhanJingdian/js/epub.min.js
AndroidBaizhanJingdian/js/epub.min.map
AndroidBaizhanJingdian/js/hooks.min.js
AndroidBaizhanJingdian/js/hooks.min.map
AndroidBaizhanJingdian/js/reader.js
AndroidBaizhanJingdian/js/reader.js.map
AndroidBaizhanJingdian/js/reader.min.js
AndroidBaizhanJingdian/js/reader.min.map
AndroidBaizhanJingdian/js/hooks/__init__.py
AndroidBaizhanJingdian/js/hooks/extensions/__init__.py
AndroidBaizhanJingdian/js/hooks/extensions/highlight.js
AndroidBaizhanJingdian/js/libs/__init__.py
AndroidBaizhanJingdian/js/libs/jquery.min.js
AndroidBaizhanJingdian/js/libs/localforage.min.js
AndroidBaizhanJingdian/js/libs/screenfull.js
AndroidBaizhanJingdian/js/libs/screenfull.min.js
AndroidBaizhanJingdian/js/libs/zip.min.js
android_baizhan_jingdian-2024.3.3.0.dist-info/METADATA
android_baizhan_jingdian-2024.3.3.0.dist-info/WHEEL
android_baizhan_jingdian-2024.3.3.0.dist-info/entry_points.txt
android_baizhan_jingdian-2024.3.3.0.dist-info/top_level.txt
android_baizhan_jingdian-2024.3.3.0.dist-info/RECORD
